fix_imports/__init__.py
fix_imports/__main__.py
fix_imports/commandline/__init__.py
fix_imports/commandline/cli.py
fix_imports/config.py
fix_imports/file.py
fix_imports/package.py
fix_imports/predefined.py
fix_imports/pyflake.py
py_fix_imports-0.1.0.dist-info/METADATA
py_fix_imports-0.1.0.dist-info/WHEEL
py_fix_imports-0.1.0.dist-info/entry_points.txt
py_fix_imports-0.1.0.dist-info/licenses/LICENSE
py_fix_imports-0.1.0.dist-info/RECORD
