Metadata-Version: 2.1
Name: py-fix-imports
Version: 0.1.0
Summary: python tool and library that will fix your imports
Author-Email: Rishabh <jharishabh672003@gmail.com>
License: GPL-3.0-only
Requires-Python: >=3.12
Requires-Dist: click>=8.1.7
Requires-Dist: pyflakes>=3.2.0
Requires-Dist: importlib>=1.0.4
Requires-Dist: xdg-base-dirs>=6.0.1
